README.rst
setup.cfg
setup.py
boinet_monitoring/BalanceCalculatorBySubjectType.py
boinet_monitoring/BalancesCalculator.py
boinet_monitoring/Plotter.py
boinet_monitoring/__init__.py
boinet_monitoring/__main__.py
boinet_monitoring/cli.py
boinet_monitoring/events_reader.py
boinet_monitoring/terminal_printer.py
wasupu_boinet_monitoring.egg-info/PKG-INFO
wasupu_boinet_monitoring.egg-info/SOURCES.txt
wasupu_boinet_monitoring.egg-info/dependency_links.txt
wasupu_boinet_monitoring.egg-info/requires.txt
wasupu_boinet_monitoring.egg-info/top_level.txt