Metadata-Version: 1.1
Name: wasupu-boinet-monitoring
Version: 0.3.0
Summary: Reporting tool for wasupu-boinet
Home-page: UNKNOWN
Author: UNKNOWN
Author-email: UNKNOWN
License: Apache-2
Keywords: monitoring,cli,boinet
Platform: UNKNOWN
Classifier: Intended Audience :: Developers
Classifier: Intended Audience :: Information Technology
Classifier: Operating System :: OS Independent
Classifier: Programming Language :: Python
